{
	"required": true,
	"package": "virtuoel.towelette.mixin",
	"compatibilityLevel": "JAVA_8",
	"plugin": "virtuoel.towelette.mixin.ToweletteMixinConfigPlugin",
	"mixins":
	[
		"AnvilBlockMixin",
		"AttachedStemBlockMixin",
		"BambooBlockMixin",
		"BambooSaplingBlockMixin",
		"BaseFluidMixin",
		"BedBlockMixin",
		"BlockItemMixin",
		"BlockMixin",
		"BlockStateMixin",
		"BucketItemMixin",
		"CampfireBlockMixin",
		"CropBlockMixin",
		"DoorBlockMixin",
		"DragonEggBlockMixin",
		"EntityMixin",
		"FallingBlockEntityMixin",
		"FireBlockMixin",
		"FlowerPotBlockMixin",
		"FluidMixin",
		"PistonBlockEntityMixin",
		"PistonBlockMixin",
		"SlabBlockMixin",
		"StateManagerBuilderMixin",
		"StemBlockMixin",
		"TallBlockItemMixin",
		"TallPlantMixin",
		"TrapdoorBlockMixin",
		"TripwireHookBlockMixin",
		"VoxelShapeAccessor",
		"WorldMixin",
		"compat116plus.WeepingVinesBlockMixin",
		"compat116plus.WeepingVinesPlantBlockMixin",
		"fluidloggable.FluidloggableMixin",
		"fluidloggable.AllOfTheBlocksMixin",
		"fluidloggable.BarrierBlockMixin",
		"fluidloggable.BeaconBlockMixin",
		"fluidloggable.CauldronBlockMixin",
		"fluidloggable.EndPortalBlockMixin",
		"fluidloggable.FarmlandBlockMixin",
		"fluidloggable.FireBlockMixin",
		"fluidloggable.GrassPathBlockMixin",
		"fluidloggable.HoneyBlockMixin",
		"fluidloggable.LeavesBlockMixin",
		"fluidloggable.LilyPadBlockMixin",
		"fluidloggable.NetherPortalBlockMixin",
		"fluidloggable.ObserverBlockMixin",
		"fluidloggable.PistonBlockMixin",
		"fluidloggable.RedstoneBlockMixin",
		"fluidloggable.RedstoneWireBlockMixin",
		"fluidloggable.ShulkerBoxBlockMixin",
		"fluidloggable.SlimeBlockMixin",
		"fluidloggable.SpawnerBlockMixin",
		"fluidloggable.StructureVoidBlockMixin",
		"fluidloggable.TorchBlockMixin",
		"fluidloggable.compat116plus.FluidloggableMixin"
	],
	"injectors":
	{
		"defaultRequire": 1
	}
}
